{
  "幺樂団カァニバル！1": {
    "name": "幺樂団カァニバル！1",
    "date": "2010.09.05",
    "circles": [
      {
        "name": "愛のある風景",
        "pen_name": "けーたく",
        "circle_url": "http://ainoarufukei.web.fc2.com/",
        "position": "樂21",
        "block": "ア行"
      },
      {
        "name": "あおしんごう",
        "pen_name": "IG",
        "circle_url": "http://blog.livedoor.jp/m-87_09611/",
        "position": "樂14",
        "block": "ア行"
      },
      {
        "name": "赤字救済倶楽部",
        "pen_name": "こいづみあこ",
        "circle_url": "http://homepage3.nifty.com/AkoKoizumi/",
        "position": "幺15",
        "block": "ア行"
      },
      {
        "name": "明日やろう。",
        "pen_name": "tyottone",
        "circle_url": "http://com.nicovideo.jp/community/co53454",
        "position": "幺03",
        "block": "ア行"
      },
      {
        "name": "あったかフード",
        "pen_name": "白望フライ",
        "circle_url": "http://hothood.r.ribbon.to/index.html",
        "position": "幺17",
        "block": "ア行"
      },
      {
        "name": "杏ぱん箱",
        "pen_name": "saku",
        "circle_url": "http://osakelove.blog34.fc2.com/",
        "position": "団01",
        "block": "ア行"
      },
      {
        "name": "苺十字総本舗",
        "pen_name": "剣愁",
        "circle_url": "",
        "position": "幺20",
        "block": "ア行"
      },
      {
        "name": "Water.Club.",
        "pen_name": "T.T",
        "circle_url": "",
        "position": "団10",
        "block": "ア行"
      },
      {
        "name": "鶯壱里",
        "pen_name": "廿秒",
        "circle_url": "http://ichiri.sakura.ne.jp",
        "position": "樂24",
        "block": "ア行"
      },
      {
        "name": "8bit canvas",
        "pen_name": "8bit",
        "circle_url": "http://itigox.com",
        "position": "樂12",
        "block": "ア行"
      },
      {
        "name": "えふえふえふ",
        "pen_name": "木五倍子",
        "circle_url": "http://blog-fff.seesaa.net/",
        "position": "樂09",
        "block": "ア行"
      },
      {
        "name": "大熊猫飯店",
        "pen_name": "岡平 閑",
        "circle_url": "http://pandaza.hanagumori.com/",
        "position": "樂10",
        "block": "ア行"
      },
      {
        "name": "大盛二丁",
        "pen_name": "木ノ下さく夜",
        "circle_url": "",
        "position": "幺10",
        "block": "ア行"
      },
      {
        "name": "おっちゃんの唄",
        "pen_name": "流れ者",
        "circle_url": "http://www.geocities.jp/occyannouta/",
        "position": "樂07",
        "block": "ア行"
      },
      {
        "name": "海老亭",
        "pen_name": "ワヤナジン",
        "circle_url": "http://blog.livedoor.jp/ishiihiromasa58-ediary/archives/669866.html",
        "position": "樂05",
        "block": "カ行"
      },
      {
        "name": "型K式",
        "pen_name": "カタケイ",
        "circle_url": "http://wagocolo218.blog70.fc2.com/",
        "position": "団02",
        "block": "カ行"
      },
      {
        "name": "彼之庵",
        "pen_name": "秋坂たくみ",
        "circle_url": "http://kanoan.sakura.ne.jp/",
        "position": "幺07",
        "block": "カ行"
      },
      {
        "name": "紙そうび",
        "pen_name": "お紙",
        "circle_url": "http://kamibukuro727.blog50.fc2.com/",
        "position": "幺12",
        "block": "カ行"
      },
      {
        "name": "喜栄座cmp",
        "pen_name": "喜栄座",
        "circle_url": "http://kasumi.sakura.ne.jp/~kieyza/default.htm",
        "position": "団28.27",
        "block": "カ行"
      },
      {
        "name": "桔梗の花の咲くところ",
        "pen_name": "葉月 梗",
        "circle_url": "http://kikyou-fg.hp.infoseek.co.jp/",
        "position": "樂03",
        "block": "カ行"
      },
      {
        "name": "刻刻音樂館",
        "pen_name": "samidare",
        "circle_url": "http://www42.tok2.com/home/samidaremidi/",
        "position": "団13",
        "block": "カ行"
      },
      {
        "name": "Kissing the\n  Mirror",
        "pen_name": "Wooming",
        "circle_url": "http://www.aod666.com",
        "position": "団09",
        "block": "カ行"
      },
      {
        "name": "Gallery Culter",
        "pen_name": "Culter",
        "circle_url": "http://yannosu1012.karou.jp/",
        "position": "樂27",
        "block": "カ行"
      },
      {
        "name": "9bFOX",
        "pen_name": "ふっかん",
        "circle_url": "http://www.myspace.com/9bfox",
        "position": "団11",
        "block": "カ行"
      },
      {
        "name": "Cynthia",
        "pen_name": "桜木李杏",
        "circle_url": "http://cynthia.cc/",
        "position": "団07",
        "block": "カ行"
      },
      {
        "name": "ぎんのしずく",
        "pen_name": "神依レラみつきよいみ",
        "circle_url": "http://yuki.kitune.info/ginsizu/",
        "position": "幺05",
        "block": "カ行"
      },
      {
        "name": "空中線とらきゃっと",
        "pen_name": "トラネコ",
        "circle_url": "http://ku-chu-sen.com/",
        "position": "団18",
        "block": "カ行"
      },
      {
        "name": "ぐちょまぜ猫貴族",
        "pen_name": "内藤めあ",
        "circle_url": "http://gutyomazenekokizoku.web.fc2.com/",
        "position": "樂17",
        "block": "カ行"
      },
      {
        "name": "クラムボンの微笑",
        "pen_name": "とはらのたみ",
        "circle_url": "http://toharan.blog.shinobi.jp/",
        "position": "樂18",
        "block": "カ行"
      },
      {
        "name": "グリーンマート高橋",
        "pen_name": "玖",
        "circle_url": "http://natsume.ushimairi.com/",
        "position": "団17",
        "block": "カ行"
      },
      {
        "name": "くるぶし",
        "pen_name": "ken(偽205)",
        "circle_url": "http://homepage2.nifty.com/cafecelica/kurubushi01.html",
        "position": "幺02",
        "block": "カ行"
      },
      {
        "name": "幻想ノ郷茶話会",
        "pen_name": "有井 哲也",
        "circle_url": "http://ninth-gen-teaparty.info/",
        "position": "樂01",
        "block": "カ行"
      },
      {
        "name": "仔犬工房",
        "pen_name": "ビーグル",
        "circle_url": "http://beegle7.blog122.fc2.com/",
        "position": "幺09",
        "block": "カ行"
      },
      {
        "name": "黒命館",
        "pen_name": "葵 大樹",
        "circle_url": "http://aoimotoki.blog99.fc2.com/",
        "position": "幺22",
        "block": "カ行"
      },
      {
        "name": "さーくる単純冥界!",
        "pen_name": "砲牙",
        "circle_url": "http://yellow.ribbon.to/~houga/",
        "position": "幺04",
        "block": "サ行"
      },
      {
        "name": "3104丁目のDANCEHALL",
        "pen_name": "忠之介",
        "circle_url": "http://dancehallin3104st.blog50.fc2.com/",
        "position": "団03",
        "block": "サ行"
      },
      {
        "name": "SEA SPARROWS",
        "pen_name": "内火艇",
        "circle_url": "http://www.sea-spa.jp",
        "position": "団12",
        "block": "サ行"
      },
      {
        "name": "柴犬革命",
        "pen_name": "ウータン",
        "circle_url": "http://shibakaku.blog118.fc2.com/",
        "position": "幺14",
        "block": "サ行"
      },
      {
        "name": "島根農機",
        "pen_name": "ともぞ〜",
        "circle_url": "",
        "position": "樂22",
        "block": "サ行"
      },
      {
        "name": "じゃあくやみぐんだん",
        "pen_name": "ふるふろんタル",
        "circle_url": "",
        "position": "団26",
        "block": "サ行"
      },
      {
        "name": "しゅがーオーガスト",
        "pen_name": "さヴぃー",
        "circle_url": "http://wasavi.ame-zaiku.com/",
        "position": "樂04",
        "block": "サ行"
      },
      {
        "name": "juniperberry",
        "pen_name": "ゴルジ体",
        "circle_url": "http://juniperberry.blog.shinobi.jp/",
        "position": "団22",
        "block": "サ行"
      },
      {
        "name": "しろ.こばこ",
        "pen_name": "しろあいさ",
        "circle_url": "http://siroaisa.web.fc2.com/",
        "position": "団08",
        "block": "サ行"
      },
      {
        "name": "真空管ロジック",
        "pen_name": "キタ",
        "circle_url": "http://kitalab.blog63.fc2.com/",
        "position": "樂06",
        "block": "サ行"
      },
      {
        "name": "GINGER ALE",
        "pen_name": "しょうが",
        "circle_url": "",
        "position": "幺11",
        "block": "サ行"
      },
      {
        "name": "〜studio〜SunFlower",
        "pen_name": "謙虚な変人",
        "circle_url": "http://studio-sunflower.dojin.com/",
        "position": "幺25",
        "block": "サ行"
      },
      {
        "name": "蒼魔館",
        "pen_name": "影宮正樹",
        "circle_url": "http://smallcherry01.blog18.fc2.com/",
        "position": "幺13",
        "block": "サ行"
      },
      {
        "name": "怠惰性月兎",
        "pen_name": "有希崎",
        "circle_url": "http://taidaseigetto.blog111.fc2.com",
        "position": "樂08",
        "block": "タ行"
      },
      {
        "name": "Type夢",
        "pen_name": "煌篭",
        "circle_url": "http://www.pixiv.net/member.php?id=785551",
        "position": "樂15",
        "block": "タ行"
      },
      {
        "name": "卵たっぷり",
        "pen_name": "かに玉",
        "circle_url": "http://canitama.blog57.fc2.com/",
        "position": "樂25",
        "block": "タ行"
      },
      {
        "name": "臆病者なげっつ",
        "pen_name": "霧華",
        "circle_url": "http://f19.aaa.livedoor.jp/~nagets/",
        "position": "団24",
        "block": "タ行"
      },
      {
        "name": "月見酒",
        "pen_name": "Lam.",
        "circle_url": "http://www.tsukimizake.com/",
        "position": "樂19",
        "block": "タ行"
      },
      {
        "name": "月夜美之風",
        "pen_name": "風月闇夜",
        "circle_url": "http://blog.surpara.com/ayal_blog/",
        "position": "団20",
        "block": "タ行"
      },
      {
        "name": "ツナ缶の缶切り",
        "pen_name": "石川ひろあき",
        "circle_url": "http://blog.livedoor.jp/tunakannkiri/",
        "position": "幺18",
        "block": "タ行"
      },
      {
        "name": "Tsubameyado",
        "pen_name": "燕山君",
        "circle_url": "",
        "position": "幺16",
        "block": "タ行"
      },
      {
        "name": "電波カオス",
        "pen_name": "ぃゃぅ",
        "circle_url": "http://chaos9dempa.sakura.ne.jp/137/",
        "position": "樂28",
        "block": "タ行"
      },
      {
        "name": "東方焼大福",
        "pen_name": "鉄 鉄仁",
        "circle_url": "http://blog.livedoor.jp/kuroganedou/",
        "position": "幺26",
        "block": "タ行"
      },
      {
        "name": "特異功能組&黒白工房",
        "pen_name": "冰川冥",
        "circle_url": "http://taiwan-toho.symphonic-net.com/moe_style_01/",
        "position": "幺27",
        "block": "タ行"
      },
      {
        "name": "奈種殻",
        "pen_name": "栗名月",
        "circle_url": "http://natanegara.iinaa.net/",
        "position": "団06",
        "block": "ナ行"
      },
      {
        "name": "ねこだいすき",
        "pen_name": "ねこま",
        "circle_url": "http://www.pixiv.net/member.php?id=33802",
        "position": "樂13",
        "block": "ナ行"
      },
      {
        "name": "白米御殿",
        "pen_name": "ればにら",
        "circle_url": "http://members.jcom.home.ne.jp/nirareba/",
        "position": "樂23",
        "block": "ハ行"
      },
      {
        "name": "ハテノハテ星雲",
        "pen_name": "スジャータ",
        "circle_url": "",
        "position": "幺28",
        "block": "ハ行"
      },
      {
        "name": "ばみり",
        "pen_name": "ツバネ",
        "circle_url": "http://bamiri.net/",
        "position": "樂11",
        "block": "ハ行"
      },
      {
        "name": "久幸繙文",
        "pen_name": "久樹輝幸",
        "circle_url": "http://www.akyu.info/",
        "position": "樂02",
        "block": "ハ行"
      },
      {
        "name": "ひだりきき用",
        "pen_name": "麻宮守",
        "circle_url": "",
        "position": "幺06",
        "block": "ハ行"
      },
      {
        "name": "ひめくり姫街道",
        "pen_name": "あぎょう 山犬",
        "circle_url": "http://himekurihime.web.fc2.com/index.html",
        "position": "幺01",
        "block": "ハ行"
      },
      {
        "name": "ファンシー★忍者",
        "pen_name": "花木",
        "circle_url": "http://misah.littlestar.jp/index.htm",
        "position": "幺19",
        "block": "ハ行"
      },
      {
        "name": "ふあん亭",
        "pen_name": "フラリ",
        "circle_url": "http://www7b.biglobe.ne.jp/hurahura/",
        "position": "団21",
        "block": "ハ行"
      },
      {
        "name": "Vagramt Of\n  Nameless",
        "pen_name": "お気楽ゾンビ",
        "circle_url": "",
        "position": "団05",
        "block": "ハ行"
      },
      {
        "name": "星海月",
        "pen_name": "へもぐろびんA1C",
        "circle_url": "http://hosikurage.xxxxxxxx.jp/",
        "position": "幺21",
        "block": "ハ行"
      },
      {
        "name": "無題No-title",
        "pen_name": "鴉城K子",
        "circle_url": "",
        "position": "団04",
        "block": "マ行"
      },
      {
        "name": "柳瀬川",
        "pen_name": "みるきゃら",
        "circle_url": "http://yanagisegawa.6.ql.bz//",
        "position": "団16",
        "block": "ヤ行"
      },
      {
        "name": "やぶしらず",
        "pen_name": "ちぶるすきぃ",
        "circle_url": "http://yabushirazu.blog110.fc2.com/",
        "position": "樂16",
        "block": "ヤ行"
      },
      {
        "name": "優戯",
        "pen_name": "新刻 慧",
        "circle_url": "http://keiyuugi.blog62.fc2.com/",
        "position": "幺24",
        "block": "ヤ行"
      },
      {
        "name": "Yohitama",
        "pen_name": "ヨヒノリ",
        "circle_url": "http://yohitama.nobody.jp/",
        "position": "団25",
        "block": "ヤ行"
      },
      {
        "name": "LOVE eater",
        "pen_name": "片桐 修",
        "circle_url": "",
        "position": "団19",
        "block": "ラ行"
      },
      {
        "name": "涼夏亭",
        "pen_name": "片瀬かの",
        "circle_url": "http://odhin.zero-yen.com/",
        "position": "樂20",
        "block": "ラ行"
      },
      {
        "name": "LunarComet",
        "pen_name": "小谷悠",
        "circle_url": "http://kstd.net/",
        "position": "団14",
        "block": "ラ行"
      },
      {
        "name": "れいんぼうてぃー",
        "pen_name": "ちびねこ",
        "circle_url": "",
        "position": "幺23",
        "block": "ラ行"
      },
      {
        "name": "狼月庵",
        "pen_name": "Gentle_Wolf",
        "circle_url": "http://dokokasiranohenkyou.blog66.fc2.com/",
        "position": "樂26",
        "block": "ラ行"
      },
      {
        "name": "腋があったら挟まりたい。",
        "pen_name": "フジヴァ",
        "circle_url": "http://wakihasa.sakura.ne.jp/",
        "position": "幺08",
        "block": "ワ行"
      }
    ]
  },
  "幺樂団カァニバル！2": {
    "name": "幺樂団カァニバル！2",
    "date": "2011.05.22",
    "circles": [
      {
        "position": "幺01",
        "name": "えふえふえふ",
        "circle_url": "http://blog-fff.seesaa.net/"
      },
      {
        "position": "幺02",
        "name": "星海月",
        "circle_url": "http://hosikurage.xxxxxxxx.jp/"
      },
      {
        "position": "幺03",
        "name": "a-TTTempo",
        "circle_url": "http://projectshion.xxxxxxxx.jp/"
      },
      {
        "position": "幺04",
        "name": "魔界在住",
        "circle_url": "http://blog.goo.ne.jp/shinki_th05"
      },
      {
        "position": "幺05",
        "name": "狼月庵",
        "circle_url": "http://dokokasiranohenkyou.blog66.fc2.com/"
      },
      {
        "position": "幺06",
        "name": "暮れ雨。",
        "circle_url": "http://4696.manjushage.com/"
      },
      {
        "position": "幺07",
        "name": "柳瀬川",
        "circle_url": "http://yanagisegawa.6.ql.bz/"
      },
      {
        "position": "幺08",
        "name": "ハテノハテ星雲",
        "circle_url": "http://hatenohatenohate.blog134.fc2.com/"
      },
      {
        "position": "幺09",
        "name": "猟奇的妄想症候群",
        "circle_url": "http://usamirenko.com/"
      },
      {
        "position": "幺11",
        "name": "峠桜屋",
        "circle_url": "http://www.yukian.com/"
      },
      {
        "position": "幺12",
        "name": "NECO湘南",
        "circle_url": "http://project-k.osakazu.com/"
      },
      {
        "position": "幺13.14",
        "name": "れいんぼうてぃー",
        "circle_url": "http://rainbow-nizitya.at.webry.info/201101/article_1.html"
      },
      {
        "position": "幺15",
        "name": "杏パン箱",
        "circle_url": "http://osakelove.blog34.fc2.com/"
      },
      {
        "position": "幺16",
        "name": "影紡糸&SevenStars!!!!!!!",
        "circle_url": "http://7hoshi.blog.shinobi.jp/"
      },
      {
        "position": "幺18",
        "name": "シャこ",
        "circle_url": "http://shako.iza-yoi.net/"
      },
      {
        "position": "幺19",
        "name": "KEMONOMICHI",
        "circle_url": "http://kemono666.blog70.fc2.com/"
      },
      {
        "position": "幺20",
        "name": "ふあん亭",
        "circle_url": "http://www7b.biglobe.ne.jp/~hurahura/"
      },
      {
        "position": "樂01",
        "name": "大熊猫飯店",
        "circle_url": "http://pandaza.hanagumori.com/"
      },
      {
        "position": "樂05",
        "name": "P_c_R",
        "circle_url": "http://j02.nobody.jp/index.htm"
      },
      {
        "position": "樂07",
        "name": "ちょこびゐる",
        "circle_url": "http://chocobeer.3rin.net/"
      },
      {
        "position": "樂08",
        "name": "Gallery Culter",
        "circle_url": "http://yannosu1012.karou.jp/"
      },
      {
        "position": "樂09",
        "name": "やぶしらず",
        "circle_url": "http://yabushirazu.blog110.fc2.com/"
      },
      {
        "position": "樂10",
        "name": "どくだみ茶",
        "circle_url": "http://ameblo.jp/me75di4/"
      },
      {
        "position": "樂11",
        "name": "涼夏亭",
        "circle_url": "http://odhin.zero-yen.com/"
      },
      {
        "position": "樂12",
        "name": "W・さーきゅぅれーしょん",
        "circle_url": "http://windcirculation.blog.shinobi.jp/"
      },
      {
        "position": "樂13",
        "name": "島根農機",
        "circle_url": "http://www.pixiv.net/member.php?id=213027"
      },
      {
        "position": "樂14",
        "name": "Cynthia",
        "circle_url": "http://cynthia.cc/"
      },
      {
        "position": "樂15",
        "name": "聖宵純華",
        "circle_url": "http://glfarld.blog100.fc2.com/"
      },
      {
        "position": "樂17",
        "name": "ファンシー★忍者",
        "circle_url": "http://misah.littlestar.jp/index.htm"
      },
      {
        "position": "樂18",
        "name": "すとろべりー",
        "circle_url": "http://000strawberry000.web.fc2.com/"
      },
      {
        "position": "樂19",
        "name": "柴犬革命",
        "circle_url": "http://shibakaku.blog118.fc2.com/"
      },
      {
        "position": "樂20",
        "name": "くるぶし",
        "circle_url": "http://homepage2.nifty.com/cafecelica/kurubushi01.html"
      },
      {
        "position": "樂21",
        "name": "明日やろう。",
        "circle_url": "http://ashitayarimasen.blog87.fc2.com/"
      },
      {
        "position": "樂22",
        "name": "七輪大社",
        "circle_url": "http://sichirin.blog45.fc2.com/"
      },
      {
        "position": "樂24",
        "name": "Tsubameyado",
        "circle_url": "http://www.pixiv.net/member.php?id=99283"
      },
      {
        "position": "樂25",
        "name": "腋があったら挟まりたい。",
        "circle_url": "http://blog.livedoor.jp/wakihasa/"
      },
      {
        "position": "樂26",
        "name": "冬まっただなか",
        "circle_url": "http://whiterocky.blog7.fc2.com/"
      },
      {
        "position": "樂27",
        "name": "アマオト。",
        "circle_url": "http://waterdrop.blog.shinobi.jp/"
      },
      {
        "position": "樂28",
        "name": "梯屋",
        "circle_url": "http://hashiya.cava.jp/"
      },
      {
        "position": "樂29",
        "name": "空廻不器用三世",
        "circle_url": "http://kuromi99.syoyu.net/"
      },
      {
        "position": "樂31",
        "name": "黒命館",
        "circle_url": "http://aoimotoki.blog99.fc2.com/"
      },
      {
        "position": "樂32",
        "name": "片道飛行",
        "circle_url": "http://oriemuy.blog41.fc2.com/"
      },
      {
        "position": "樂34",
        "name": "卵たっぷり",
        "circle_url": "http://canitama.blog57.fc2.com/"
      },
      {
        "position": "樂35",
        "name": "東方焼大福",
        "circle_url": "http://blog.livedoor.jp/kuroganedou/"
      },
      {
        "position": "樂36",
        "name": "真空管ロジック",
        "circle_url": "http://kitalab.blog63.fc2.com/"
      },
      {
        "position": "団02",
        "name": "明度良好",
        "circle_url": "http://maid-ryoukou.sakura.ne.jp/blog/"
      },
      {
        "position": "団03",
        "name": "ペペロンチーノ・キャンディ",
        "circle_url": "http://peperoncinocandy.web.fc2.com/index.html"
      },
      {
        "position": "団04",
        "name": "久幸繙文",
        "circle_url": "http://www.akyu.info/"
      },
      {
        "position": "団05",
        "name": "キミロリ",
        "circle_url": "http://honobonokeikaku.cocolog-nifty.com/kimirori/"
      },
      {
        "position": "団07.08",
        "name": "奈種殻",
        "circle_url": "http://natanegara.iinaa.net/"
      },
      {
        "position": "団09",
        "name": "型Ｋ式",
        "circle_url": "http://wagocolo218.blog70.fc2.com/"
      },
      {
        "position": "団10",
        "name": "怠惰性月兎",
        "circle_url": "http://taidaseigetto.blog111.fc2.com/"
      },
      {
        "position": "団11",
        "name": "しろ．こばこ",
        "circle_url": "http://siroaisa.web.fc2.com/"
      },
      {
        "position": "団12",
        "name": "かうじょん",
        "circle_url": "http://rakugakisuruei.blog98.fc2.com/"
      },
      {
        "position": "団14",
        "name": "シャレコーベ草原",
        "circle_url": "http://www.pixiv.net/member.php?id=858310"
      },
      {
        "position": "団15",
        "name": "ロウズ自虐",
        "circle_url": "http://sicknesswhiteout.blog98.fc2.com/"
      },
      {
        "position": "団16",
        "name": "星芋剣士",
        "circle_url": "http://crazycol0rs.blog45.fc2.com/"
      },
      {
        "position": "団18",
        "name": "魔導琥珀研究所",
        "circle_url": "http://homepage2.nifty.com/sabokoha/"
      },
      {
        "position": "団19.20",
        "name": "喜栄座cmp",
        "circle_url": "http://kasumi.sakura.ne.jp/~kieyza/default.htm"
      },
      {
        "position": "団21",
        "name": "キタガワジマ",
        "circle_url": "http://kitagawajima.ko-me.com/"
      },
      {
        "position": "団22",
        "name": "ばみり",
        "circle_url": "http://bamiri.net/"
      },
      {
        "position": "団23",
        "name": "ぴくとりえ",
        "circle_url": "http://www.pixiv.net/member.php?id=253991"
      },
      {
        "position": "団25",
        "name": "まぐなむお～ぱす",
        "circle_url": "http://homepage1.nifty.com/TAKA-S/"
      },
      {
        "position": "団26",
        "name": "命の限り好き勝手",
        "circle_url": "http://ameblo.jp/leavatein/"
      },
      {
        "position": "団27",
        "name": "B地区",
        "circle_url": "http://foxof.sitemix.jp/blog/"
      },
      {
        "position": "団28",
        "name": "月面着陸ファージ",
        "circle_url": "http://mocchie.rejec.net/"
      },
      {
        "position": "団29",
        "name": "as qool as qucumber",
        "circle_url": "http://acacmizu.blog130.fc2.com/"
      },
      {
        "position": "団30",
        "name": "鶯壱里",
        "circle_url": "http://ichiri.sakura.ne.jp/"
      },
      {
        "position": "団31",
        "name": "生パン庫",
        "circle_url": "http://namapann.com/"
      },
      {
        "position": "団32",
        "name": "刻刻音樂館",
        "circle_url": "http://www42.tok2.com/home/samidaremidi/"
      },
      {
        "position": "団34",
        "name": "神楽庭園",
        "circle_url": "http://kagura.secret.jp/"
      },
      {
        "position": "団35.36",
        "name": "UnLimited Questions/STARWALKER STUDIO",
        "circle_url": "http://harupaca.blog42.fc2.com/"
      }
    ]
  },
  "幺樂団カァニバル！3": {
    "name": "幺樂団カァニバル！3",
    "date": "2012.05.06",
    "circles": [
      { "position": "が10", "name": "明日やろう。" },
      { "position": "だ05", "name": "as Qool as Qucumber" },
      { "position": "う12", "name": "(あの)" },
      { "position": "が03,04", "name": "天水" },
      { "position": "く16", "name": "命の限り好き勝手。" },
      { "position": "が08", "name": "VODKA" },
      { "position": "く07", "name": "V.O.N" },
      { "position": "だ01,02", "name": "鶯壱里" },
      { "position": "よ06", "name": "8bit canvas" },
      { "position": "だ04", "name": "悦楽舎" },
      { "position": "よ18", "name": "えふえふえふ" },
      { "position": "よ01", "name": "大熊猫飯店＆Register6" },
      { "position": "う03", "name": "大盛二丁" },
      { "position": "う13", "name": "オリエント鈍行" },
      { "position": "が13", "name": "OriginZero&TinyWave" },
      { "position": "が15", "name": "音速スローカーブ！！" },
      { "position": "が01", "name": "かうじょん" },
      { "position": "よ17", "name": "型K式" },
      { "position": "ん07,08", "name": "喜栄座cmp" },
      { "position": "ん01", "name": "桔梗の花の咲くところ" },
      { "position": "ん06", "name": "キタガワジマ" },
      { "position": "く10", "name": "キミロリ" },
      { "position": "う18", "name": "Gallery Culter" },
      { "position": "く11", "name": "Cynthia" },
      { "position": "ん03", "name": "くずなり" },
      { "position": "が16", "name": "くるぶし" },
      { "position": "よ16", "name": "暮れ雨。" },
      { "position": "だ08", "name": "月面着陸ファージ" },
      { "position": "く08", "name": "紅茶党" },
      { "position": "が17", "name": "黒命館" },
      { "position": "ん04", "name": "咲耶17歳" },
      { "position": "く01", "name": "しうまいを継ぐ者" },
      { "position": "く02", "name": "七輪大社" },
      { "position": "う01", "name": "柴犬革命" },
      { "position": "う09", "name": "シャレコーベ草原" },
      { "position": "が18", "name": "出血観察日記" },
      { "position": "よ13,14", "name": "少女屋本舗" },
      { "position": "よ03", "name": "真空管ロジック" },
      { "position": "く06", "name": "すいさんかおうぶつ" },
      { "position": "う15", "name": "Scarlet Moon" },
      { "position": "だ06", "name": "スタジオネネム" },
      { "position": "が02", "name": "02小隊" },
      { "position": "が06", "name": "センかる" },
      { "position": "う07", "name": "月宇佐城" },
      { "position": "が11", "name": "月ヶ瀬工房" },
      { "position": "う04", "name": "ツナ缶の缶切り" },
      { "position": "く13", "name": "D.C.S.ひななゐや" },
      { "position": "よ04", "name": "東方焼大福" },
      { "position": "だ07", "name": "外柿山" },
      { "position": "う17", "name": "どくだみ茶" },
      { "position": "く15", "name": "とび爆ぜっ" },
      { "position": "よ11,12", "name": "奈種殻" },
      { "position": "く09", "name": "ノンフィクションレーザー" },
      { "position": "よ15", "name": "覇王軒" },
      { "position": "う08", "name": "パズライズ＆Convallo-stick" },
      { "position": "よ08", "name": "ばみり" },
      { "position": "く18", "name": "久幸繙文＆幻想ノ郷茶話会" },
      { "position": "が07", "name": "ファビフビ" },
      { "position": "よ07", "name": "ふあん亭" },
      { "position": "く12", "name": "Princess and Medium" },
      { "position": "が09", "name": "星芋剣士" },
      { "position": "く03", "name": "骨マン" },
      { "position": "だ03", "name": "まぐなむお～ぱす" },
      { "position": "う10", "name": "マジクルシィ" },
      { "position": "ん02", "name": "魔導琥珀研究" },
      { "position": "く04", "name": "麿醤油店" },
      { "position": "う16", "name": "Myosotis" },
      { "position": "く05", "name": "夢幻回顧" },
      { "position": "う05", "name": "むせんぶ" },
      { "position": "う14", "name": "MEMENT MORI" },
      { "position": "よ02", "name": "柳瀬川" },
      { "position": "が14", "name": "夢追工房" },
      { "position": "く14", "name": "寄集堂本舗" },
      { "position": "く17", "name": "ラストオーダーはとつぜんに" },
      { "position": "が05", "name": "涼夏亭" },
      { "position": "よ09,10", "name": "れいんぼうてぃー×わぁるうぃんど" },
      { "position": "う11", "name": "ロウズ自虐" },
      { "position": "ん05", "name": "YTD" },
      { "position": "が12", "name": "腋があったら挟まりたい。" },
      { "position": "う02", "name": "わすれな部屋" }
    ]
  },
  "幺樂団カァニバル！4": {
    "name": "幺樂団カァニバル！4",
    "date": "2013.04.21",
    "circles": null
  },
  "幺樂団カァニバル！5": {
    "name": "幺樂団カァニバル！5",
    "date": "2014.09.14",
    "circles": [
      {
        "name": "久幸繙文＆幻想ノ郷茶話会",
        "position": "幺1",
        "pen_name": "久樹 輝幸",
        "circle_url": "http://www.akyu.info/sawakai/link"
      },
      {
        "name": "わぁるうぃんど",
        "position": "幺2",
        "pen_name": "それ",
        "circle_url": ""
      },
      {
        "name": "袋の鼠",
        "position": "幺3",
        "pen_name": "鼠",
        "circle_url": ""
      },
      {
        "name": "五花八門",
        "position": "幺4",
        "pen_name": "上條　紗智",
        "circle_url": "http://blogs.yahoo.co.jp/circle_goka"
      },
      {
        "name": "死体安置所",
        "position": "幺5",
        "pen_name": "礫死体",
        "circle_url": "http://v54h5gh4m.blog.fc2.com/"
      },
      {
        "name": "空色ねぎ",
        "position": "幺6",
        "pen_name": "タカシバ",
        "circle_url": "http://www.pixiv.net/member.php?id=2568481"
      },
      {
        "name": "むせんぶ",
        "position": "幺7",
        "pen_name": "Dill",
        "circle_url": ""
      },
      {
        "name": "島根農機",
        "position": "幺8",
        "pen_name": "ともぞ～",
        "circle_url": "http://www.pixiv.net/member.php?id=213027"
      },
      {
        "name": "シャレコーベ草原",
        "position": "幺9",
        "pen_name": "donjuan",
        "circle_url": "http://blogs.yahoo.co.jp/bassclarinet12"
      },
      {
        "name": "ロウズ自虐",
        "position": "幺10",
        "pen_name": "酒井 風",
        "circle_url": "http://www.pixiv.net/member.php?id=801346"
      },
      {
        "name": "帰ってきた豆腐大明神２０１４&星芋剣士",
        "position": "幺11.12",
        "pen_name": "TragosiTouf",
        "circle_url": ""
      },
      {
        "name": "笑花奇観",
        "position": "幺13",
        "pen_name": "風守 夏璃",
        "circle_url": ""
      },
      {
        "name": "外柿山",
        "position": "幺14",
        "pen_name": "権太夫",
        "circle_url": "http://togakisan.blog.fc2.com/"
      },
      {
        "name": "H2O",
        "position": "幺15",
        "pen_name": "みず",
        "circle_url": "http://pcr.iinaa.net/"
      },
      {
        "name": "壱萬通",
        "position": "幺16",
        "pen_name": "takaiman",
        "circle_url": "http://www.pixiv.net/member.php?id=416532"
      },
      {
        "name": "ここから先、34小節目。",
        "position": "幺17",
        "pen_name": "あぶらあげ",
        "circle_url": "http://www.geocities.jp/average_34measure/"
      },
      {
        "name": "涼夏亭",
        "position": "幺18",
        "pen_name": "片瀬　かの",
        "circle_url": "http://ryo-ka.sakura.ne.jp/"
      },
      {
        "name": "キミロリ",
        "position": "幺19",
        "pen_name": "遅上 なぎさ",
        "circle_url": "http://honobonokeikaku.cocolog-nifty.com/kimirori/"
      },
      {
        "name": "Cynthia",
        "position": "幺20",
        "pen_name": "桜木李杏",
        "circle_url": "http://cynthia.cc/"
      },
      {
        "name": "Narcissus",
        "position": "樂1",
        "pen_name": "片岡　昴",
        "circle_url": ""
      },
      {
        "name": "夢幻回顧",
        "position": "樂2",
        "pen_name": "哀愁鴉天狗",
        "circle_url": "http://www.pixiv.net/member.php?id=997598"
      },
      {
        "name": "七輪大社",
        "position": "樂3",
        "pen_name": "Y2",
        "circle_url": "http://sichirin.blog45.fc2.com/"
      },
      {
        "name": "型K式",
        "position": "樂4",
        "pen_name": "カタケイ",
        "circle_url": "http://pixiv.me/wagocolo"
      },
      {
        "name": "えるれ～しょん",
        "position": "樂5",
        "pen_name": "骨尺",
        "circle_url": ""
      },
      {
        "name": "胡玉書厨",
        "position": "樂6",
        "pen_name": "胡玉",
        "circle_url": "http://www.geocities.co.jp/Bookend-Kenji/8181/"
      },
      {
        "name": "むらさきラーメン",
        "position": "樂7",
        "pen_name": "むらさき",
        "circle_url": "http://www.pixiv.net/member.php?id=251079"
      },
      {
        "name": "日々徒然。",
        "position": "樂8",
        "pen_name": "古翠",
        "circle_url": "http://hbtd16.sakura.ne.jp/"
      },
      {
        "name": "黒命館",
        "position": "樂9",
        "pen_name": "葵　大樹",
        "circle_url": ""
      },
      {
        "name": "チートイ12000",
        "position": "樂10",
        "pen_name": "refle",
        "circle_url": ""
      },
      {
        "name": "命の限り好き勝手。",
        "position": "樂11",
        "pen_name": "鈴宮　真琴",
        "circle_url": "http://ameblo.jp/leavatein/"
      },
      {
        "name": "大盛二丁",
        "position": "樂12",
        "pen_name": "木ノ下さく夜",
        "circle_url": ""
      },
      {
        "name": "Convallo-stick",
        "position": "樂13",
        "pen_name": "halogen",
        "circle_url": "http://convallostick.blog.fc2.com/"
      },
      {
        "name": "あるとれっつぇる",
        "position": "樂14",
        "pen_name": "さざしな　はる",
        "circle_url": ""
      },
      {
        "name": "柳瀬川",
        "position": "樂15",
        "pen_name": "ミルキャラ",
        "circle_url": "http://yanagisegawa.sakura.ne.jp/"
      },
      {
        "name": "02小隊",
        "position": "樂16",
        "pen_name": "WAT",
        "circle_url": ""
      },
      {
        "name": "葛成",
        "position": "樂17",
        "pen_name": "kuzuaki",
        "circle_url": ""
      },
      {
        "name": "幸福島",
        "position": "樂18",
        "pen_name": "伊豆 ジャルゴン",
        "circle_url": ""
      },
      {
        "name": "全日本MBO推奨委員会",
        "position": "樂19",
        "pen_name": "お気楽ゾンビ",
        "circle_url": "http://www.pixiv.net/member.php?id=1068183"
      },
      {
        "name": "かうじょん",
        "position": "樂20",
        "pen_name": "ぇぃたいさ",
        "circle_url": "http://rakugakisuruei.blog98.fc2.com/"
      }
    ]
  },
  "幺樂団カァニバル！6": {
    "name": "幺樂団カァニバル！6",
    "date": "2016.11.12",
    "circles": null
  },
  "幺樂団カァニバル！7": {
    "name": "幺樂団カァニバル！7",
    "date": "2017.11.11",
    "circles": [
      {
        "name": "型K式",
        "position": "祭1"
      },
      {
        "name": "出血観察日記",
        "position": "祭2"
      },
      {
        "name": "れいんぼうてぃー",
        "position": "祭3"
      },
      {
        "name": "つきみ野黄昏プラザ",
        "position": "祭4"
      },
      {
        "name": "メアリアンブルー",
        "position": "幺1&2"
      },
      {
        "name": "下り安全側線",
        "position": "幺3"
      },
      {
        "name": "本を描いてる屋さん",
        "position": "幺4"
      },
      {
        "name": "沈んだ船",
        "position": "幺5"
      },
      {
        "name": "Cynthia",
        "position": "幺6"
      },
      {
        "name": "悦楽舎",
        "position": "幺7"
      },
      {
        "name": "波赤斗",
        "position": "幺8"
      },
      {
        "name": "日和見日和",
        "position": "樂1"
      },
      {
        "name": "鎖付鉄球工房",
        "position": "樂2"
      },
      {
        "name": "しのぎ倶楽部ver.0",
        "position": "樂3"
      },
      {
        "name": "月桃プラネタリウム",
        "position": "樂4"
      },
      {
        "name": "イシュノクサ植物園",
        "position": "樂5"
      },
      {
        "name": "伊予弁普及之会",
        "position": "樂6"
      },
      {
        "name": "冥途ノ夢",
        "position": "樂7&8"
      },
      {
        "name": "抹茶雲越パフェ",
        "position": "樂9"
      },
      {
        "name": "偕楽店BURST",
        "position": "樂10"
      },
      {
        "name": "麿醤油店",
        "position": "樂11"
      },
      {
        "name": "たましぽろぎ",
        "position": "樂12"
      },
      {
        "name": "黒命館",
        "position": "樂13"
      },
      {
        "name": "北白川紋章院",
        "position": "樂14"
      },
      {
        "name": "七輪大社",
        "position": "樂15&16"
      },
      {
        "name": "武神中間体",
        "position": "樂17"
      },
      {
        "name": "とりくる屋",
        "position": "樂18"
      },
      {
        "name": "ラパパメリカ",
        "position": "樂19&20"
      },
      {
        "name": "みちく茶話会",
        "position": "樂21"
      },
      {
        "name": "ぬまうおハウス",
        "position": "樂22"
      },
      {
        "name": "五花八門",
        "position": "樂23"
      },
      {
        "name": "じゅうきゃく店",
        "position": "樂24"
      },
      {
        "name": "星芋剣士",
        "position": "団1"
      },
      {
        "name": "たろいも屋さん",
        "position": "団2"
      },
      {
        "name": "屑鉄おきば。",
        "position": "団3"
      },
      {
        "name": "9.1.NET",
        "position": "団4"
      },
      {
        "name": "生首屋",
        "position": "団5"
      },
      {
        "name": "ロウズ自虐",
        "position": "団6"
      },
      {
        "name": "Cafe Erdbeere",
        "position": "団7"
      },
      {
        "name": "内野二階席",
        "position": "団8"
      },
      {
        "name": "ビリッケツトレイン",
        "position": "団9"
      },
      {
        "name": "外柿山",
        "position": "団10"
      },
      {
        "name": "STUDIO FUNGO",
        "position": "団11"
      },
      {
        "name": "放課後日和",
        "position": "団12"
      },
      {
        "name": "胡玉書厨",
        "position": "団13"
      },
      {
        "name": "かうじょん",
        "position": "団14"
      },
      {
        "name": "しゃーぷにくびーふ",
        "position": "団15"
      },
      {
        "name": "あるとれっつぇる",
        "position": "団16"
      },
      {
        "name": "てぽ丼 ニンニクマシマシアブラスクナメヤサイオオメ",
        "position": "団17&18"
      },
      {
        "name": "柳瀬川",
        "position": "団19"
      },
      {
        "name": "Convallo-stick",
        "position": "団20"
      },
      {
        "name": "ペインフルフレーム",
        "position": "団21&22"
      },
      {
        "name": "ソープ夢幻館",
        "position": "団23"
      },
      {
        "name": "チートイ12000",
        "position": "団24"
      }
    ]
  },
  "幺樂団カァニバル！8": {
    "name": "幺樂団カァニバル！8",
    "date": "2018.09.22",
    "circles": [
      {
        "name": "UnLimited Questions+STARWALKER STUDIO",
        "position": "よ01"
      },
      {
        "name": "綿春巻",
        "position": "よ02"
      },
      {
        "name": "騒霊部員",
        "position": "よ03"
      },
      {
        "name": "みまらじ！",
        "position": "よ04"
      },
      {
        "name": "insky.",
        "position": "よ05"
      },
      {
        "name": "ビリッケツトレイン",
        "position": "よ06"
      },
      {
        "name": "月桃プラネタリウム",
        "position": "よ07"
      },
      {
        "name": "幻想アカデミア",
        "position": "よ08"
      },
      {
        "name": "武神中間体",
        "position": "う01"
      },
      {
        "name": "八寺発電所",
        "position": "う02"
      },
      {
        "name": "61073",
        "position": "う03"
      },
      {
        "name": "黒命館",
        "position": "う04"
      },
      {
        "name": "Cynthia",
        "position": "う05"
      },
      {
        "name": "しのぎ倶楽部ver.0",
        "position": "う06"
      },
      {
        "name": "イシュノクサ植物園",
        "position": "う07"
      },
      {
        "name": "伊予弁普及之会",
        "position": "う08"
      },
      {
        "name": "幻想列車",
        "position": "う09"
      },
      {
        "name": "沈んだ船",
        "position": "う10"
      },
      {
        "name": "ミルキー夢幻",
        "position": "う11"
      },
      {
        "name": "とりくる屋",
        "position": "う12"
      },
      {
        "name": "ゴリラの茶畑",
        "position": "う13"
      },
      {
        "name": "七輪大社",
        "position": "う14"
      },
      {
        "name": "杏パン箱",
        "position": "う15"
      },
      {
        "name": "れいんぼうてぃー",
        "position": "う16"
      },
      {
        "name": "抹茶雲越パフェ",
        "position": "う17"
      },
      {
        "name": "偕楽店BURST",
        "position": "う18"
      },
      {
        "name": "胡玉書厨",
        "position": "う19"
      },
      {
        "name": "屑鉄おきば。",
        "position": "う20"
      },
      {
        "name": "ロウズ自虐",
        "position": "う21"
      },
      {
        "name": "たろいも屋さん",
        "position": "う22"
      },
      {
        "name": "満月つきみ野",
        "position": "う23,24"
      },
      {
        "name": "彩矢バーニング・アイズ",
        "position": "う25"
      },
      {
        "name": "星芋剣士",
        "position": "う26"
      },
      {
        "name": "型K式",
        "position": "が01,02"
      },
      {
        "name": "冥途ノ夢",
        "position": "が03"
      },
      {
        "name": "鎖付鉄球工房",
        "position": "が04"
      },
      {
        "name": "本を描いてる屋さん",
        "position": "が05,06"
      },
      {
        "name": "Narcissus",
        "position": "が07"
      },
      {
        "name": "波赤斗",
        "position": "が08"
      },
      {
        "name": "五花八門",
        "position": "が09"
      },
      {
        "name": "灯籠通り一丁目",
        "position": "が10"
      },
      {
        "name": "じゅうきゃく店",
        "position": "が11"
      },
      {
        "name": "かいこ計",
        "position": "が12"
      },
      {
        "name": "ラパパメリカ",
        "position": "が13,14"
      },
      {
        "name": "みちく茶話会",
        "position": "が15"
      },
      {
        "name": "24G",
        "position": "が16"
      },
      {
        "name": "Sound and Vision",
        "position": "が17"
      },
      {
        "name": "外柿山",
        "position": "が18"
      },
      {
        "name": "放課後日和",
        "position": "が19"
      },
      {
        "name": "大盛二丁",
        "position": "が20"
      },
      {
        "name": "日和見日和",
        "position": "が21"
      },
      {
        "name": "夢幻倉庫",
        "position": "が22"
      },
      {
        "name": "Convallo-stick",
        "position": "が23"
      },
      {
        "name": "ペインフルフレーム",
        "position": "が24"
      },
      {
        "name": "てぽ丼3",
        "position": "が25,26"
      },
      {
        "name": "下り安全側線",
        "position": "く01,02"
      },
      {
        "name": "カタコトリ",
        "position": "く03"
      },
      {
        "name": "as Qool as Qucumber",
        "position": "く04"
      },
      {
        "name": "シスリラ",
        "position": "く05"
      }
    ]
  },
  "幺樂団カァニバル！9": {
    "name": "幺樂団カァニバル！9",
    "date": "2019.09.22",
    "circles": [
      {
        "name": "あぴゅあっ",
        "position": "人0102",
        "pen_name": "ぽんちゃん"
      },
      {
        "name": "弓弦羽Konzert",
        "position": "人03",
        "pen_name": "宿雪"
      },
      {
        "name": "利別ノ禊",
        "position": "人04",
        "pen_name": "ナマ足"
      },
      {
        "name": "PIANISSIMO",
        "position": "人05",
        "pen_name": "ルーシア"
      },
      {
        "name": "夕空18番街",
        "position": "人06",
        "pen_name": "桐葉柚乃"
      },
      {
        "name": "作者の戯事",
        "position": "人07",
        "pen_name": "作者"
      },
      {
        "name": "Atelier.800",
        "position": "人08",
        "pen_name": "蟹沢ゆうき"
      },
      {
        "name": "鈴楽庵",
        "position": "人09",
        "pen_name": "お鈴"
      },
      {
        "name": "スイミンヨクゾウシンザイ",
        "position": "人10",
        "pen_name": "aaaaam0"
      },
      {
        "name": "rabbit3",
        "position": "人11",
        "pen_name": "みと椿"
      },
      {
        "name": "れいんぼうてぃー×わぁるうぃんど",
        "position": "よ0102",
        "pen_name": "ちびねこ&それ"
      },
      {
        "name": "夢峰地帯",
        "position": "よ03",
        "pen_name": "月海玖珠"
      },
      {
        "name": "Emeraldia",
        "position": "よ04",
        "pen_name": "ElsiaLight"
      },
      {
        "name": "ちょこふぁん",
        "position": "よ05",
        "pen_name": "すばる"
      },
      {
        "name": "RED FOREST METAL ORCHESTRA",
        "position": "よ06",
        "pen_name": "RF"
      },
      {
        "name": "Chomerio",
        "position": "よ07",
        "pen_name": "りょれ"
      },
      {
        "name": "as Qool as Qucumber",
        "position": "よ08",
        "pen_name": "瑞々"
      },
      {
        "name": "ここから先、３４小節目。",
        "position": "よ09",
        "pen_name": "あぶらあげ"
      },
      {
        "name": "外柿山",
        "position": "よ10",
        "pen_name": "権太夫"
      },
      {
        "name": "Sound and Vision",
        "position": "よ11",
        "pen_name": "月姫・朱雀帝"
      },
      {
        "name": "悦楽舎",
        "position": "よ12",
        "pen_name": "hoshi＠悦楽編"
      },
      {
        "name": "型K式",
        "position": "う0102",
        "pen_name": "カタケイ"
      },
      {
        "name": "魅魔ほりっく（UnLimited Questions）",
        "position": "う0304",
        "pen_name": "みまほりっく/はるぱか"
      },
      {
        "name": "星芋剣士",
        "position": "う05",
        "pen_name": "ラフィール"
      },
      {
        "name": "たなのぽ",
        "position": "う06",
        "pen_name": "ぴぴぃ"
      },
      {
        "name": "ロウズ自虐",
        "position": "う07",
        "pen_name": "デンバット酒井風"
      },
      {
        "name": "かぶたまじゃくし",
        "position": "う08",
        "pen_name": "かぶたま"
      },
      {
        "name": "たろいも屋さん",
        "position": "う09",
        "pen_name": "コウタロー"
      },
      {
        "name": "屑鉄おきば。",
        "position": "う10",
        "pen_name": "黝無ニッケル"
      },
      {
        "name": "土曜日の眠り姫",
        "position": "う11",
        "pen_name": "神依巫女"
      },
      {
        "name": "マノリア修道院",
        "position": "う12",
        "pen_name": "M"
      },
      {
        "name": "むせんゆ～せん",
        "position": "う13",
        "pen_name": "Dill"
      },
      {
        "name": "綿春巻",
        "position": "う14",
        "pen_name": "春日夏"
      },
      {
        "name": "あまいちご倶楽部",
        "position": "う15",
        "pen_name": "あまおう"
      },
      {
        "name": "えび★ぴらふ",
        "position": "う16",
        "pen_name": "じくも"
      },
      {
        "name": "七色快男児",
        "position": "う17",
        "pen_name": "仁科将人"
      },
      {
        "name": "百歩必殺",
        "position": "う18",
        "pen_name": "長閑"
      },
      {
        "name": "向日葵畑地域鉄道部",
        "position": "う19",
        "pen_name": "江津三郎"
      },
      {
        "name": "幻想列車",
        "position": "う20",
        "pen_name": "刻ノ　幻"
      },
      {
        "name": "Citrus*BW",
        "position": "う21",
        "pen_name": "虎"
      },
      {
        "name": "行動力のある理系のお嬢様",
        "position": "う22",
        "pen_name": "松尾はるの"
      },
      {
        "name": "幻想大膳寮/ユメミナティ",
        "position": "う2324",
        "pen_name": "七曜主醤（ナナヨウヒシオノツカサ）"
      },
      {
        "name": "月桃プラネタリウム",
        "position": "う2526",
        "pen_name": "宵やま"
      },
      {
        "name": "なーなDiary",
        "position": "う27",
        "pen_name": "Nah-nA"
      },
      {
        "name": "ナトリニウム",
        "position": "う28",
        "pen_name": "リニール"
      },
      {
        "name": "",
        "position": "",
        "pen_name": ""
      },
      {
        "name": "下り安全側線",
        "position": "が0102",
        "pen_name": "赤束子"
      },
      {
        "name": "本を描いてる屋さん",
        "position": "が0304",
        "pen_name": "星ノ雫"
      },
      {
        "name": "シャレコーベ草原",
        "position": "が05",
        "pen_name": "donjuan"
      },
      {
        "name": "しらすじゃむ屋",
        "position": "が06",
        "pen_name": "ラズジャム"
      },
      {
        "name": "抹茶雲越パフェ",
        "position": "が07",
        "pen_name": "つませう."
      },
      {
        "name": "Luna olen'",
        "position": "が08",
        "pen_name": "ヨシカ"
      },
      {
        "name": "伊予弁普及之会",
        "position": "が09",
        "pen_name": "伊予弁"
      },
      {
        "name": "福乃草",
        "position": "が10",
        "pen_name": "issue"
      },
      {
        "name": "彩矢バーニング・アイズ",
        "position": "が11",
        "pen_name": "彩矢"
      },
      {
        "name": "松狐庵",
        "position": "が12",
        "pen_name": "松狐"
      },
      {
        "name": "ワルQ13",
        "position": "が13",
        "pen_name": "なそにん"
      },
      {
        "name": "島之城",
        "position": "が14",
        "pen_name": "島乃丞"
      },
      {
        "name": "金幼日",
        "position": "が15",
        "pen_name": "みあるみ"
      },
      {
        "name": "北風ライラック6550",
        "position": "が16",
        "pen_name": "浜宮南瓜"
      },
      {
        "name": "さかな店",
        "position": "が17",
        "pen_name": "カジキオニオン"
      },
      {
        "name": "夢幻廊",
        "position": "が18",
        "pen_name": "烏丸スバル"
      },
      {
        "name": "黒命館",
        "position": "が19",
        "pen_name": "葵大樹"
      },
      {
        "name": "魔界観光協会",
        "position": "が20",
        "pen_name": "セカンド"
      },
      {
        "name": "えなじ～ぽていと",
        "position": "が21",
        "pen_name": "芋丼"
      },
      {
        "name": "骨マン",
        "position": "が22",
        "pen_name": "takaiman"
      },
      {
        "name": "何も思い出せない",
        "position": "が23",
        "pen_name": "あづれ"
      },
      {
        "name": "フォレノワール",
        "position": "が24",
        "pen_name": "さっちゃん"
      },
      {
        "name": "Liliec Style",
        "position": "が25",
        "pen_name": "Buto"
      },
      {
        "name": "武神中間体",
        "position": "が26",
        "pen_name": "シリアス-武神装甲"
      },
      {
        "name": "61073",
        "position": "が27",
        "pen_name": "ナナエモン"
      },
      {
        "name": "七輪大社",
        "position": "が28",
        "pen_name": "Y2"
      },
      {
        "name": "",
        "position": "",
        "pen_name": ""
      },
      {
        "name": "偕楽店BURST",
        "position": "く01",
        "pen_name": "ワダンテ"
      },
      {
        "name": "メアリアンブルー",
        "position": "く02",
        "pen_name": "イオ"
      },
      {
        "name": "しゃーぷにくびーふ",
        "position": "く03",
        "pen_name": "そらいろ"
      },
      {
        "name": "ヤタノケモノ",
        "position": "く04",
        "pen_name": "ヤタノケ"
      },
      {
        "name": "ラパパメリカ",
        "position": "く05",
        "pen_name": "ラパメリ"
      },
      {
        "name": "みちく茶話会",
        "position": "く06",
        "pen_name": "茶野みの"
      },
      {
        "name": "雨さかさまが夢のよう",
        "position": "く07",
        "pen_name": "雨朔いめ"
      },
      {
        "name": "じゅうきゃく店",
        "position": "く08",
        "pen_name": "スタウリ"
      },
      {
        "name": "灯籠通り一丁目",
        "position": "く09",
        "pen_name": "いもどーる"
      },
      {
        "name": "不乱道",
        "position": "く10",
        "pen_name": "影・ブランドー"
      },
      {
        "name": "ネギ塩造形丼",
        "position": "く11",
        "pen_name": "negy23（ネギニーサン）"
      },
      {
        "name": "鎖付鉄球工房",
        "position": "く12",
        "pen_name": "スペキュラム合金"
      },
      {
        "name": "デスバーガー名古屋店",
        "position": "く13",
        "pen_name": "ルジ"
      },
      {
        "name": "胡玉書厨",
        "position": "く14",
        "pen_name": "胡玉"
      },
      {
        "name": "Cynthia",
        "position": "く15",
        "pen_name": "桜木李杏"
      },
      {
        "name": "",
        "position": "く16",
        "pen_name": ""
      },
      {
        "name": "放課後日和",
        "position": "く17",
        "pen_name": "ちるろり。"
      },
      {
        "name": "意注走逆",
        "position": "く18",
        "pen_name": "逆走"
      },
      {
        "name": "insky.",
        "position": "く19",
        "pen_name": "R-ika"
      },
      {
        "name": "ＢＭスクラッチメン",
        "position": "く20",
        "pen_name": "キティ青山"
      },
      {
        "name": "夢幻倉庫",
        "position": "く21",
        "pen_name": "四方黒"
      },
      {
        "name": "Convallo-stick",
        "position": "く22",
        "pen_name": "halogen"
      },
      {
        "name": "ペインフルフレーム",
        "position": "く2324",
        "pen_name": "Azukimal（アズキマル）"
      },
      {
        "name": "柳瀬川",
        "position": "く25",
        "pen_name": "ミルキャラ"
      },
      {
        "name": "クリフェさん家のきれいなからあげ",
        "position": "く26",
        "pen_name": "クリフェ"
      },
      {
        "name": "魅々魍魎",
        "position": "く2728",
        "pen_name": "魅々熊"
      }
    ]
  },
  "幺樂団カァニバル！10": {
    "name": "幺樂団カァニバル！10",
    "date": "2020.09.26",
    "circles": [
      {
        "name": "抹茶雲越パフェ"
      },
      {
        "name": "insky."
      },
      {
        "name": "みちく茶話会"
      },
      {
        "name": "大盛二丁"
      },
      {
        "name": "Narcissus"
      },
      {
        "name": "五花八門"
      },
      {
        "name": "メアリアンブルー"
      },
      {
        "name": "ゆめうるえ"
      },
      {
        "name": "型K式"
      },
      {
        "name": "柳瀬川"
      },
      {
        "name": "伊予弁普及之会"
      },
      {
        "name": "放課後日和"
      },
      {
        "name": "Sugar and Salt"
      },
      {
        "name": "七色快男児"
      },
      {
        "name": "屑鉄おきば。"
      },
      {
        "name": "下り安全側線"
      },
      {
        "name": "24G"
      },
      {
        "name": "月桃プラネタリウム"
      },
      {
        "name": "ちょこふぁん"
      },
      {
        "name": "テレピン1000ml"
      },
      {
        "name": "れいんぼうてぃー"
      },
      {
        "name": "as Qool as Qucumber"
      },
      {
        "name": "夢想夏月郷"
      },
      {
        "name": "四葉挿話"
      },
      {
        "name": "利別ノ禊"
      },
      {
        "name": "土曜日の眠り姫"
      },
      {
        "name": "シャレコーベ草原"
      },
      {
        "name": "さかな店"
      },
      {
        "name": "鎖付鉄球工房"
      }
    ]
  },
  "幺樂団カァニバル！10R": {
    "name": "幺樂団カァニバル！10R",
    "date": "2021.02.27",
    "circles": null
  },
  "幺樂団カァニバル！11": {
    "name": "幺樂団カァニバル！11",
    "date": "2022.03.27",
    "circles": [
      {
        "name": "ALQUERMES",
        "position": "人01",
        "pen_name": "みーか",
        "circle_url": ""
      },
      {
        "name": "B・G・Rock",
        "position": "人02",
        "pen_name": "ペリジー",
        "circle_url": "https://twitter.com/BGROCK_ZEROS"
      },
      {
        "name": "PIANISSIMO",
        "position": "人03",
        "pen_name": "ルーシア",
        "circle_url": ""
      },
      {
        "name": "シャレコーベ草原",
        "position": "幺01",
        "pen_name": "donjuan",
        "circle_url": "https://www.donjuantriumph.com/"
      },
      {
        "name": "夢幻18景",
        "position": "幺02",
        "pen_name": "ゼーゲン",
        "circle_url": "https://www.pixiv.net/users/12113266"
      },
      {
        "name": "屑鉄おきば。",
        "position": "幺03",
        "pen_name": "黝無ニッケル",
        "circle_url": ""
      },
      {
        "name": "テレピン1000ml",
        "position": "幺04",
        "pen_name": "蒲谷カバヂ",
        "circle_url": "http://turpentine517.blog71.fc2.com/"
      },
      {
        "name": "Cynthia",
        "position": "幺05",
        "pen_name": "桜木李杏",
        "circle_url": "http://cynthia.cc/"
      },
      {
        "name": "鎖付鉄球工房",
        "position": "幺06",
        "pen_name": "スペキュラム合金",
        "circle_url": ""
      },
      {
        "name": "Narcissus",
        "position": "幺07",
        "pen_name": "片岡昴",
        "circle_url": ""
      },
      {
        "name": "七輪大社",
        "position": "幺08",
        "pen_name": "Y2",
        "circle_url": "http://sichirin.blog45.fc2.com/"
      },
      {
        "name": "四葉挿話",
        "position": "幺09",
        "pen_name": "かむいこたん",
        "circle_url": ""
      },
      {
        "name": "土曜日の眠り姫",
        "position": "幺10",
        "pen_name": "神依巫女",
        "circle_url": "https://kamuimiko.wixsite.com/sleepingprincesssat"
      },
      {
        "name": "常葉日和",
        "position": "幺11",
        "pen_name": "赤川羽蘭",
        "circle_url": ""
      },
      {
        "name": "月桃プラネタリウム",
        "position": "幺12",
        "pen_name": "宵やま",
        "circle_url": ""
      },
      {
        "name": "七色快男児",
        "position": "幺13",
        "pen_name": "仁科将人",
        "circle_url": ""
      },
      {
        "name": "胡玉書厨",
        "position": "幺14",
        "pen_name": "胡玉",
        "circle_url": "http://kodamagohan.g2.xrea.com/"
      },
      {
        "name": "はじけ組っ！",
        "position": "幺15",
        "pen_name": "はじけ☆あきら",
        "circle_url": "https://twitter.com/a_hazike"
      },
      {
        "name": "コルモランド",
        "position": "幺16",
        "pen_name": "コルモラン",
        "circle_url": "https://twitter.com/KormoranX"
      },
      {
        "name": "思いついたままnote",
        "position": "樂01",
        "pen_name": "土生タケヒロ",
        "circle_url": "http://s30rou.s21.xrea.com/"
      },
      {
        "name": "ゆめうるえ",
        "position": "樂02",
        "pen_name": "そらのゆめこ",
        "circle_url": ""
      },
      {
        "name": "星空らぼらとりー",
        "position": "樂03",
        "pen_name": "Duskia",
        "circle_url": ""
      },
      {
        "name": "夢峰地帯研究室",
        "position": "樂04",
        "pen_name": "るーくす",
        "circle_url": "http://muhouchitai.moo.jp/"
      },
      {
        "name": "春空天文部",
        "position": "樂05",
        "pen_name": "みつき",
        "circle_url": ""
      },
      {
        "name": "24G",
        "position": "樂06",
        "pen_name": "おそがみなぎさ",
        "circle_url": ""
      },
      {
        "name": "メアリアンブルー",
        "position": "樂07",
        "pen_name": "五百野イオ",
        "circle_url": ""
      },
      {
        "name": "しゃーぷにくびーふ",
        "position": "樂08",
        "pen_name": "そらいろ",
        "circle_url": "https://shiosyakeyakini.info/"
      },
      {
        "name": "外柿山",
        "position": "樂09",
        "pen_name": "権太夫",
        "circle_url": "http://togakisan.blog.fc2.com/"
      },
      {
        "name": "as Qool as Qucumber",
        "position": "樂10",
        "pen_name": "瑞々",
        "circle_url": "http://acacmizu.blog130.fc2.com/"
      },
      {
        "name": "ろりすこんぷれっくす",
        "position": "樂11",
        "pen_name": "ささるの",
        "circle_url": ""
      },
      {
        "name": "insky.",
        "position": "団01",
        "pen_name": "R-ika",
        "circle_url": "https://www.pixiv.net/users/10842"
      },
      {
        "name": "ほうとうネットワーク",
        "position": "団02",
        "pen_name": "諸星一",
        "circle_url": "http://blog.livedoor.jp/houtou_network/"
      },
      {
        "name": "Convallo-stick",
        "position": "団03",
        "pen_name": "halogen",
        "circle_url": "http://convallostick.blog.fc2.com/"
      },
      {
        "name": "大盛二丁",
        "position": "団04",
        "pen_name": "木ノ下さく夜",
        "circle_url": ""
      },
      {
        "name": "幻想大膳寮/ユメミナティ",
        "position": "団05",
        "pen_name": "七曜主醤",
        "circle_url": ""
      },
      {
        "name": "みちく茶話会",
        "position": "団06",
        "pen_name": "茶野みの",
        "circle_url": "https://michikusawakai.info/"
      }
    ]
  },
  "幺樂団カァニバル！12": {
    "name": "幺樂団カァニバル！12",
    "date": "2023.07.09",
    "circles": [
      {
        "name": "シャレコーベ草原",
        "position": "幺0102",
        "pen_name": "donjuan",
        "circle_url": "https://www.donjuantriumph.com/"
      },
      {
        "name": "ロウズ自虐",
        "position": "幺03",
        "pen_name": "デンバット酒井風",
        "circle_url": ""
      },
      {
        "name": "外柿山",
        "position": "幺04",
        "pen_name": "権太夫",
        "circle_url": "http://togakisan.blog.fc2.com/"
      },
      {
        "name": "カタコトリ",
        "position": "幺05",
        "pen_name": "夜覩カタリ",
        "circle_url": "https://twitter.com/suwa_moriya"
      },
      {
        "name": "Cynthia",
        "position": "幺06",
        "pen_name": "桜木李杏",
        "circle_url": "http://cynthia.cc/"
      },
      {
        "name": "蜂合わせ",
        "position": "幺07",
        "pen_name": "満希ナオ",
        "circle_url": "http://hatiawase.blog15.fc2.com/"
      },
      {
        "name": "ゆめうるえ",
        "position": "幺08",
        "pen_name": "そらのゆめこ",
        "circle_url": "https://twitter.com/soranoyumeko"
      },
      {
        "name": "幻想大膳寮",
        "position": "幺0910",
        "pen_name": "七曜主醤",
        "circle_url": ""
      },
      {
        "name": "どくいちごがぁでん",
        "position": "幺11",
        "pen_name": "ドクロちゃん",
        "circle_url": ""
      },
      {
        "name": "コーギーと共に",
        "position": "幺12",
        "pen_name": "ＣＶ",
        "circle_url": "https://twitter.com/CV0912"
      },
      {
        "name": "型K式",
        "position": "幺1314",
        "pen_name": "カタケイ",
        "circle_url": "https://twitter.com/wagocolo"
      },
      {
        "name": "れいんぼうてぃー",
        "position": "幺15",
        "pen_name": "ちびねこ",
        "circle_url": ""
      },
      {
        "name": "星空らぼらとりー",
        "position": "幺16",
        "pen_name": "Duskia",
        "circle_url": "https://twitter.com/MagusofTwilight"
      },
      {
        "name": "思いついたままnote",
        "position": "幺17",
        "pen_name": "土生タケヒロ",
        "circle_url": "http://s30rou.s21.xrea.com/"
      },
      {
        "name": "つきみ野黄昏プラザ",
        "position": "幺18",
        "pen_name": "ゆずピィ",
        "circle_url": ""
      },
      {
        "name": "四葉挿話",
        "position": "幺19",
        "pen_name": "かむいこたん",
        "circle_url": "https://twitter.com/kamu_kotan"
      },
      {
        "name": "はじけ組っ！",
        "position": "幺20",
        "pen_name": "はじけ☆あきら",
        "circle_url": ""
      },
      {
        "name": "常葉日和",
        "position": "幺21",
        "pen_name": "赤川羽蘭",
        "circle_url": ""
      },
      {
        "name": "子羊の眠り歌",
        "position": "幺22",
        "pen_name": "にゃいぐる",
        "circle_url": ""
      },
      {
        "name": "山桜ビール工房",
        "position": "幺23",
        "pen_name": "山桜ぱぱ",
        "circle_url": "https://twitter.com/sakura_beers"
      },
      {
        "name": "鎖付鉄球工房",
        "position": "幺24",
        "pen_name": "スペキュラム合金",
        "circle_url": ""
      },
      {
        "name": "燕煙夢暖簾",
        "position": "樂01",
        "pen_name": "夢魂",
        "circle_url": ""
      },
      {
        "name": "春空夢見月",
        "position": "樂02",
        "pen_name": "みつき",
        "circle_url": ""
      },
      {
        "name": "常行丼",
        "position": "樂03",
        "pen_name": "ネモ",
        "circle_url": ""
      },
      {
        "name": "メアリアンブルー",
        "position": "樂04",
        "pen_name": "五百野イオ",
        "circle_url": ""
      },
      {
        "name": "夢峰地帯研究所",
        "position": "樂05",
        "pen_name": "るーくす",
        "circle_url": ""
      },
      {
        "name": "ヤタノケモノ",
        "position": "樂06",
        "pen_name": "ヤタノケ",
        "circle_url": "https://twitter.com/yata_zetta"
      },
      {
        "name": "ぼうしやヘンリィ",
        "position": "樂07",
        "pen_name": "Jekyll",
        "circle_url": ""
      },
      {
        "name": "波赤斗",
        "position": "樂08",
        "pen_name": "takaiman",
        "circle_url": ""
      },
      {
        "name": "胡玉書厨",
        "position": "樂09",
        "pen_name": "胡玉",
        "circle_url": "https://www.pixiv.net/users/12842117"
      },
      {
        "name": "七色快男児",
        "position": "樂10",
        "pen_name": "仁科将人",
        "circle_url": ""
      },
      {
        "name": "一匹鶏のアトリエ",
        "position": "樂11",
        "pen_name": "鶏のまさ",
        "circle_url": "https://twitter.com/ippikiniwatori"
      },
      {
        "name": "月桃プラネタリウム",
        "position": "団01",
        "pen_name": "宵やま",
        "circle_url": ""
      },
      {
        "name": "Miraflores",
        "position": "団02",
        "pen_name": "Nadine",
        "circle_url": "https://twitter.com/nemonadi"
      },
      {
        "name": "Convallo-stick",
        "position": "団03",
        "pen_name": "halogen",
        "circle_url": "http://convallostick.blog.fc2.com/"
      },
      {
        "name": "みるく茶話会",
        "position": "団04",
        "pen_name": "ちなみの",
        "circle_url": "https://twitter.com/et_chinamino"
      }
    ]
  },
  "幺樂団カァニバル！13": {
    "name": "幺樂団カァニバル！13",
    "date": "2024.07.15",
    "circles": [
      {
        "name": "ALQUERMES",
        "pen_name": "みーか"
      },
      {
        "name": "Convallo-stick",
        "pen_name": "halogen"
      },
      {
        "name": "Cynthia",
        "pen_name": "桜木李杏"
      },
      {
        "name": "DUO/Waltz",
        "pen_name": "SAIFISU"
      },
      {
        "name": "End of My Lilith",
        "pen_name": "れう すずらぎ"
      },
      {
        "name": "FINE MOTION",
        "pen_name": "ファインモーション"
      },
      {
        "name": "Miraflores",
        "pen_name": "Nadine"
      },
      {
        "name": "Narcissus",
        "pen_name": "片岡昴"
      },
      {
        "name": "TC-401",
        "pen_name": "快速いわき行き"
      },
      {
        "name": "Team*ぱわー",
        "pen_name": "ヨシ力"
      },
      {
        "name": "アオイロリボン",
        "pen_name": "うさろりぃ"
      },
      {
        "name": "アルベダリン",
        "pen_name": "みかんポン"
      },
      {
        "name": "えなじ～ぽていと",
        "pen_name": "芋丼"
      },
      {
        "name": "おきし団",
        "pen_name": "おきし"
      },
      {
        "name": "お華見会場",
        "pen_name": "阿亀華"
      },
      {
        "name": "カタコトリ",
        "pen_name": "夜覩カタリ"
      },
      {
        "name": "カタルシス少年戯樂団",
        "pen_name": "音屋のばけばけ"
      },
      {
        "name": "グリュンハール",
        "pen_name": "アイディス"
      },
      {
        "name": "コーギーと共に",
        "pen_name": "ＣＶ"
      },
      {
        "name": "コルモランド",
        "pen_name": "コルモラン"
      },
      {
        "name": "さんよんさん",
        "pen_name": "サンクス"
      },
      {
        "name": "シャレコーベ草原",
        "pen_name": "donjuan"
      },
      {
        "name": "チートイ12000",
        "pen_name": "りふれ"
      },
      {
        "name": "つきみ野黄昏プラザ",
        "pen_name": "ゆずピィ"
      },
      {
        "name": "どくいちごがぁでん",
        "pen_name": "ドクロちゃん"
      },
      {
        "name": "とろもち炉",
        "pen_name": "千里めると"
      },
      {
        "name": "はじけ組っ！",
        "pen_name": "はじけ☆あきら"
      },
      {
        "name": "ぴょこっとついんて！",
        "pen_name": "ぴょこっとついんて！"
      },
      {
        "name": "フォレノワール",
        "pen_name": "はーちゃん"
      },
      {
        "name": "ぼうしやヘンリィ",
        "pen_name": "Jekyll"
      },
      {
        "name": "みちく茶話会",
        "pen_name": "茶野みの"
      },
      {
        "name": "もちもちGarage",
        "pen_name": "もちお"
      },
      {
        "name": "ロウズ自虐",
        "pen_name": "デンバット酒井風"
      },
      {
        "name": "ろりすこんぷれっくす",
        "pen_name": "ささるの"
      },
      {
        "name": "わぁるうぃんど",
        "pen_name": "それ"
      },
      {
        "name": "隠匿菜園",
        "pen_name": "せろり"
      },
      {
        "name": "燕煙夢暖簾",
        "pen_name": "夢魂"
      },
      {
        "name": "外柿山",
        "pen_name": "権太夫"
      },
      {
        "name": "企画院総裁官房",
        "pen_name": "コッシー"
      },
      {
        "name": "屑鉄おきば。",
        "pen_name": "黝無ニッケル"
      },
      {
        "name": "型K式",
        "pen_name": "カタケイ"
      },
      {
        "name": "胡玉書厨",
        "pen_name": "胡玉"
      },
      {
        "name": "五花八門",
        "pen_name": "上條紗智"
      },
      {
        "name": "鎖付鉄球工房",
        "pen_name": "スペキュラム合金"
      },
      {
        "name": "子羊の眠り歌",
        "pen_name": "にゃいぐる"
      },
      {
        "name": "思いついたままnote",
        "pen_name": "土生タケヒロ"
      },
      {
        "name": "七色快男児",
        "pen_name": "仁科将人"
      },
      {
        "name": "春空夢見月",
        "pen_name": "みつき"
      },
      {
        "name": "少女Revolver",
        "pen_name": "つるぎん"
      },
      {
        "name": "常行丼×深想芯理",
        "pen_name": "ネモ"
      },
      {
        "name": "常葉日和×れいんぼうてぃー",
        "pen_name": "赤川羽蘭"
      },
      {
        "name": "人生三日坊主",
        "pen_name": "まんぷくちゃん"
      },
      {
        "name": "星空らぼらとりー",
        "pen_name": "Duskia"
      },
      {
        "name": "星神様の神徳",
        "pen_name": "めりめり"
      },
      {
        "name": "大吉座",
        "pen_name": "T.D"
      },
      {
        "name": "地球侵略",
        "pen_name": "博士"
      },
      {
        "name": "放課後日和",
        "pen_name": "ちるろり"
      },
      {
        "name": "本を描いてる屋さん",
        "pen_name": "星ノ雫"
      },
      {
        "name": "魔法猫みぃぃ手描きイラスト倶楽部",
        "pen_name": "魔法猫みぃぃ"
      },
      {
        "name": "夢峰地帯研究所",
        "pen_name": "るーくす"
      }
    ]
  },
  "幺樂団カァニバル！14": {
    "name": "幺樂団カァニバル！14",
    "date": "2025.06.29",
    "circles": [
      {
        "name": "外柿山",
        "position": "よ01",
        "pen_name": "権太夫"
      },
      {
        "name": "ここから先、34小節目。",
        "position": "よ02",
        "pen_name": "あぶらあげ"
      },
      {
        "name": "FINE MOTION",
        "position": "よ03",
        "pen_name": "neko neko knife"
      },
      {
        "name": "K2E†Cradle",
        "position": "よ04",
        "pen_name": "MIKOTO"
      },
      {
        "name": "提燈屋",
        "position": "よ05",
        "pen_name": "る〜へい"
      },
      {
        "name": "櫓INDUSTRY",
        "position": "よ06",
        "pen_name": "cübe"
      },
      {
        "name": "Crystallize",
        "position": "よ0708",
        "pen_name": "ちょこれーしょん"
      },
      {
        "name": "カタルシス少年戯樂団",
        "position": "よ0910",
        "pen_name": "音屋のばけばけ"
      },
      {
        "name": "ぴょこっとついんて！",
        "position": "う0102",
        "pen_name": "ぴょこっとついんて"
      },
      {
        "name": "星屑喫茶時間",
        "position": "う03",
        "pen_name": "白風真白"
      },
      {
        "name": "どくいちごがぁでん",
        "position": "う04",
        "pen_name": "ドクロちゃん"
      },
      {
        "name": "隠匿菜園",
        "position": "う05",
        "pen_name": "せろり"
      },
      {
        "name": "春空夢見月",
        "position": "う06",
        "pen_name": "みつき"
      },
      {
        "name": "アオイロリボン",
        "position": "う07",
        "pen_name": "うさろりぃ"
      },
      {
        "name": "スタヂオほむら",
        "position": "う08",
        "pen_name": "うずみび"
      },
      {
        "name": "ALQUERMES",
        "position": "う0910",
        "pen_name": "みーか"
      },
      {
        "name": "24G",
        "position": "う11",
        "pen_name": "桂木うくう"
      },
      {
        "name": "星空らぼらとりー",
        "position": "う12",
        "pen_name": "Duskia"
      },
      {
        "name": "蓄光性梅ソーダ",
        "position": "う13",
        "pen_name": "莱人"
      },
      {
        "name": "常行丼",
        "position": "う14",
        "pen_name": "ネモ"
      },
      {
        "name": "五花八門",
        "position": "う15",
        "pen_name": "上條紗智"
      },
      {
        "name": "林檎雨",
        "position": "う16",
        "pen_name": "真澄"
      },
      {
        "name": "常葉日和＆LOW＋",
        "position": "が0102",
        "pen_name": "赤川羽蘭"
      },
      {
        "name": "はじけ組っ！",
        "position": "が03",
        "pen_name": "はじけ☆あきら"
      },
      {
        "name": "フォレノワール",
        "position": "が04",
        "pen_name": "はーちゃん"
      },
      {
        "name": "グリュンハール",
        "position": "が05",
        "pen_name": "アイディス"
      },
      {
        "name": "PIANISSIMO",
        "position": "が06",
        "pen_name": "ルーシア"
      },
      {
        "name": "本を描いてる屋さん",
        "position": "が0708",
        "pen_name": "星丿雫"
      },
      {
        "name": "Cynthia",
        "position": "が09",
        "pen_name": "桜木李杏"
      },
      {
        "name": "つきみ野黄昏プラザ",
        "position": "が10",
        "pen_name": "ゆずピィ"
      },
      {
        "name": "Emerald May",
        "position": "が11",
        "pen_name": "いおり"
      },
      {
        "name": "お華見会場",
        "position": "が12",
        "pen_name": "阿亀華"
      },
      {
        "name": "ナトリニウム",
        "position": "が13",
        "pen_name": "リニール"
      },
      {
        "name": "とろもち炉",
        "position": "が14",
        "pen_name": "千里めると"
      },
      {
        "name": "幻想大膳寮",
        "position": "が15",
        "pen_name": "土師大膳七曜"
      },
      {
        "name": "たかはま",
        "position": "が16",
        "pen_name": "みかん飴"
      },
      {
        "name": "心病神社",
        "position": "く0102",
        "pen_name": "魅々熊"
      },
      {
        "name": "地球侵略",
        "position": "く03",
        "pen_name": "博士"
      },
      {
        "name": "空想デリバリー",
        "position": "く04",
        "pen_name": "水沢メルカ"
      },
      {
        "name": "もちもちGarage",
        "position": "く05",
        "pen_name": "もちお"
      },
      {
        "name": "お家で待っててね",
        "position": "く06",
        "pen_name": "るすばん"
      },
      {
        "name": "七色快男児",
        "position": "く07",
        "pen_name": "仁科将人"
      },
      {
        "name": "胡玉書厨",
        "position": "く08",
        "pen_name": "胡玉"
      },
      {
        "name": "MSD-Works",
        "position": "く09",
        "pen_name": "めしだ"
      },
      {
        "name": "七輪大社",
        "position": "く10",
        "pen_name": "Y2"
      },
      {
        "name": "アルベダリン",
        "position": "く11",
        "pen_name": "みかんポン"
      },
      {
        "name": "屑鉄おきば。",
        "position": "く12",
        "pen_name": "黝無ニッケル"
      },
      {
        "name": "ロウズ自虐",
        "position": "く13",
        "pen_name": "デンバット酒井風"
      },
      {
        "name": "型K式",
        "position": "く1516",
        "pen_name": "カタケイ"
      },
      {
        "name": "みちく茶話会",
        "position": "だ01",
        "pen_name": "茶野みの"
      },
      {
        "name": "Tc-401",
        "position": "だ02",
        "pen_name": "快速いわき行き"
      },
      {
        "name": "おきし団",
        "position": "だ03",
        "pen_name": "おきし"
      },
      {
        "name": "綺羅星の館",
        "position": "だ04",
        "pen_name": "諸星一"
      },
      {
        "name": "えなじ～ぽていと",
        "position": "だ0506",
        "pen_name": "芋丼"
      }
    ]
  }
}
